redlines/__init__.py
redlines/cli.py
redlines/document.py
redlines/processor.py
redlines/redlines.py
redlines-0.5.1.dist-info/LICENSE.txt
redlines-0.5.1.dist-info/METADATA
redlines-0.5.1.dist-info/WHEEL
redlines-0.5.1.dist-info/entry_points.txt
redlines-0.5.1.dist-info/RECORD
