Metadata-Version: 2.1
Name: redlines
Version: 0.5.1
Summary: Compare text, and produce human-readable differences or deltas which look like track changes in Microsoft Word.
Home-page: https://houfu.github.io/redlines/
License: MIT
Author: houfu
Author-email: houfu@outlook.sg
Requires-Python: >=3.8,<4.0
Classifier: License :: OSI Approved :: MIT License
Classifier: Programming Language :: Python :: 3
Classifier: Programming Language :: Python :: 3.8
Classifier: Programming Language :: Python :: 3.9
Classifier: Programming Language :: Python :: 3.10
Classifier: Programming Language :: Python :: 3.11
Classifier: Programming Language :: Python :: 3.12
Classifier: Programming Language :: Python :: 3.13
Requires-Dist: click (>=8.1.3,<9.0.0)
Requires-Dist: rich (>=13.3.5,<14.0.0)
Requires-Dist: rich-click (>=1.6.1,<2.0.0)
Project-URL: Repository, https://github.com/houfu/redlines
